swiftest/CMakeLists.txt
swiftest/__init__.py
swiftest/_version.py
swiftest/cli.py
swiftest/constants.py
swiftest/core.cpython-312-aarch64-linux-gnu.so
swiftest/core.h
swiftest/core.pyx
swiftest/data.py
swiftest/init_cond.py
swiftest/io.py
swiftest/shgrav.py
swiftest/simulation.py
swiftest/swiftest
swiftest/tool.py
swiftest/visualize.py
swiftest.libs/libblosc-be004a45.so.1.21.6
swiftest.libs/libcrypto-3dc39733.so.1.1.1k
swiftest.libs/libevent_core-2-57d925e3.1.so.6.0.2
swiftest.libs/libevent_pthreads-2-7a90c0ed.1.so.6.0.2
swiftest.libs/libfftw3-b7546720.so.3.5.5
swiftest.libs/libgfortran-8a9a71bc.so.5.0.0
swiftest.libs/libgomp-947d5fa1.so.1.0.0
swiftest.libs/libhdf5-032ea218.so.310.5.1
swiftest.libs/libhdf5_hl-f06268b3.so.310.0.6
swiftest.libs/libhwloc-8ede5728.so.15.2.0
swiftest.libs/libmpi-3623eac1.so.40.30.1
swiftest.libs/libmpi_mpifh-45be33d2.so.40.30.0
swiftest.libs/libmpi_usempi_ignore_tkr-9498d3bb.so.40.30.0
swiftest.libs/libmpi_usempif08-db3a2a28.so.40.30.0
swiftest.libs/libnetcdf-63c693c8.so.22
swiftest.libs/libnetcdff-8c4f3d86.so.7.1.0
swiftest.libs/libopen-orted-mpir-23b85609.so
swiftest.libs/libopen-pal-28c1764f.so.40.30.1
swiftest.libs/libopen-rte-6676d576.so.40.30.1
swiftest.libs/libopenblas-r0-e9c9f581.3.15.so
swiftest.libs/libswiftest-b288a82d.so
swiftest.libs/libzstd-531dc13c.so.1.5.7
swiftest-2025.10.1.dist-info/METADATA
swiftest-2025.10.1.dist-info/WHEEL
swiftest-2025.10.1.dist-info/entry_points.txt
swiftest-2025.10.1.dist-info/RECORD
swiftest-2025.10.1.dist-info/licenses/COPYING
swiftest-2025.10.1.dist-info/licenses/LICENSE
