Metadata-Version: 2.2
Name: swiftest
Version: 2025.10.1
Summary: Swiftest is a software packaged designed to model the long-term dynamical dynamics of n-body systems with a dominant central body, like the solar system.
Keywords: astronomy,astrophysics,planetary,n-body,integrator,symplectic,wisdom-holman,symba
Author: Carlisle Wishard, Jennifer Pouplin, Jake Elliott, Dana Singh, Kaustub Anand
Author-Email: "David A. Minton" <daminton@purdue.edu>
Maintainer-Email: "David A. Minton" <daminton@purdue.edu>
License: Copyright 2025 - David Minton 
Classifier: Development Status :: 4 - Beta
Classifier: Intended Audience :: Science/Research
Classifier: Topic :: Scientific/Engineering :: Astronomy
Classifier: License :: OSI Approved :: GNU General Public License v3 or later (GPLv3+)
Classifier: Programming Language :: Python :: 3
Project-URL: repository, https://github.com/MintonGroup/swiftest
Project-URL: documentation, https://swiftest.readthedocs.io/en/latest/
Project-URL: changelog, https://swiftest.readthedocs.io/en/latest/whats-new.html
Requires-Python: >=3.11
Requires-Dist: numpy
Requires-Dist: xarray>=2024.10.0
Requires-Dist: scipy
Requires-Dist: h5py<3.15,>=3.12.1
Requires-Dist: netcdf4
Requires-Dist: h5netcdf
Requires-Dist: dask
Requires-Dist: distributed
Requires-Dist: bottleneck
Requires-Dist: matplotlib
Requires-Dist: astropy>=6
Requires-Dist: astroquery
Requires-Dist: tqdm
Requires-Dist: cython>=3
Requires-Dist: pywinpty; platform_system == "Windows"
Provides-Extra: pyshtools
Requires-Dist: pyshtools>=4.13.1; extra == "pyshtools"
